Metadata-Version: 2.4
Name: autofix-python-engine
Version: 1.0.0
Summary: Automatic Python error detection and fixing
Author: Amit Rosen
Project-URL: Homepage, https://github.com/Amitro123/autofix-python-engine
Keywords: python,error-fixing,automation,cli
Classifier: Development Status :: 4 - Beta
Classifier: Intended Audience :: Developers
Classifier: Programming Language :: Python :: 3
Requires-Python: >=3.8
